indy_community/__init__.py
indy_community/admin.py
indy_community/agent_utils.py
indy_community/apps.py
indy_community/forms.py
indy_community/indy_state.py
indy_community/indy_utils.py
indy_community/ledger_utils.py
indy_community/models.py
indy_community/registration_utils.py
indy_community/signals.py
indy_community/tasks.py
indy_community/urls.py
indy_community/utils.py
indy_community/views.py
indy_community/wallet_utils.py
indy_community/fixtures/__init__.py
indy_community/indy_cat/__init__.py
indy_community/indy_cat/error.py
indy_community/indy_cat/storage/__init__.py
indy_community/indy_cat/storage/base.py
indy_community/indy_cat/storage/basic.py
indy_community/indy_cat/storage/error.py
indy_community/indy_cat/storage/indy.py
indy_community/indy_cat/storage/record.py
indy_community/indy_cat/storage/tests/__init__.py
indy_community/indy_cat/storage/tests/storage_tests.py
indy_community/management/__init__.py
indy_community/management/commands/__init__.py
indy_community/management/commands/loads_orgs.py
indy_community/management/commands/loads_schemas.py
indy_community/migrations/0001_initial.py
indy_community/migrations/0002_auto_20190319_2207.py
indy_community/migrations/0003_auto_20190327_1332.py
indy_community/migrations/0004_auto_20190328_0248.py
indy_community/migrations/0005_auto_20190409_0051.py
indy_community/migrations/0006_auto_20190413_0001.py
indy_community/migrations/0007_auto_20190413_0125.py
indy_community/migrations/0008_indyorganization_ico_url.py
indy_community/migrations/0009_auto_20190430_0331.py
indy_community/migrations/__init__.py
indy_community/templates/.DS_Store
indy_community/templates/base_landing.html
indy_community/templates/base_nav.html
indy_community/templates/indy/.DS_Store
indy_community/templates/indy/base_individual_profile.html
indy_community/templates/indy/base_organization_profile.html
indy_community/templates/indy/data.html
indy_community/templates/indy/form_response.html
indy_community/templates/indy/profile.html
django_indy_community-0.1.14.dist-info/LICENSE
django_indy_community-0.1.14.dist-info/METADATA
django_indy_community-0.1.14.dist-info/WHEEL
django_indy_community-0.1.14.dist-info/top_level.txt
django_indy_community-0.1.14.dist-info/RECORD
