Metadata-Version: 2.1
Name: django-indy-community
Version: 0.1.14
Summary: A simple Django package to build web-based Indy agent applications.
Home-page: https://github.com/AnonSolutions/django-indy-community
Author: Ian Costanzo
Author-email: ian@anon-solutions.ca
License: 996.ICU License
Platform: UNKNOWN
Classifier: Environment :: Web Environment
Classifier: Framework :: Django
Classifier: Intended Audience :: Developers
Classifier: License :: Other/Proprietary License
Classifier: Operating System :: Unix
Classifier: Operating System :: MacOS
Classifier: Programming Language :: Python
Classifier: Programming Language :: Python :: 3.5
Classifier: Programming Language :: Python :: 3.6
Classifier: Topic :: Internet :: WWW/HTTP
